zkan/__init__.py
zkan/__main__.py
zkan-1.0.1.dist-info/LICENSE
zkan-1.0.1.dist-info/METADATA
zkan-1.0.1.dist-info/WHEEL
zkan-1.0.1.dist-info/entry_points.txt
zkan-1.0.1.dist-info/top_level.txt
zkan-1.0.1.dist-info/RECORD
